<annotation>
	<folder>0ttt</folder>
	<filename>281.JPG</filename>
	<path>281.JPG</path>
	<source>
		<database>Unknown</database>
	</source>
	<size>
		<width>1920</width>
		<height>1080</height>
		<depth>3</depth>
	</size>
	<segmented>0</segmented>
	<object>
		<name>6_patch</name>
		<pose>Unspecified</pose>
		<truncated>0</truncated>
		<difficult>0</difficult>
		<bndbox>
			<xmin>543</xmin>
			<ymin>813</ymin>
			<xmax>771</xmax>
			<ymax>846</ymax>
		</bndbox>
	</object>
	<object>
		<name>6_patch</name>
		<pose>Unspecified</pose>
		<truncated>0</truncated>
		<difficult>0</difficult>
		<bndbox>
			<xmin>1095</xmin>
			<ymin>796</ymin>
			<xmax>1287</xmax>
			<ymax>828</ymax>
		</bndbox>
	</object>
	<object>
		<name>6_patch</name>
		<pose>Unspecified</pose>
		<truncated>0</truncated>
		<difficult>0</difficult>
		<bndbox>
			<xmin>508</xmin>
			<ymin>878</ymin>
			<xmax>658</xmax>
			<ymax>1063</ymax>
		</bndbox>
	</object>
	<object>
		<name>6_patch</name>
		<pose>Unspecified</pose>
		<truncated>0</truncated>
		<difficult>0</difficult>
		<bndbox>
			<xmin>849</xmin>
			<ymin>841</ymin>
			<xmax>1073</xmax>
			<ymax>1006</ymax>
		</bndbox>
	</object>
	<object>
		<name>6_patch</name>
		<pose>Unspecified</pose>
		<truncated>0</truncated>
		<difficult>0</difficult>
		<bndbox>
			<xmin>1059</xmin>
			<ymin>821</ymin>
			<xmax>1303</xmax>
			<ymax>968</ymax>
		</bndbox>
	</object>
	<object>
		<name>6_patch</name>
		<pose>Unspecified</pose>
		<truncated>0</truncated>
		<difficult>0</difficult>
		<bndbox>
			<xmin>1324</xmin>
			<ymin>981</ymin>
			<xmax>1467</xmax>
			<ymax>1070</ymax>
		</bndbox>
	</object>
	<object>
		<name>6_patch</name>
		<pose>Unspecified</pose>
		<truncated>0</truncated>
		<difficult>0</difficult>
		<bndbox>
			<xmin>1419</xmin>
			<ymin>826</ymin>
			<xmax>1643</xmax>
			<ymax>928</ymax>
		</bndbox>
	</object>
	<object>
		<name>6_patch</name>
		<pose>Unspecified</pose>
		<truncated>0</truncated>
		<difficult>0</difficult>
		<bndbox>
			<xmin>1021</xmin>
			<ymin>725</ymin>
			<xmax>1150</xmax>
			<ymax>757</ymax>
		</bndbox>
	</object>
</annotation>