<annotation>
	<folder>images</folder>
	<filename>53.JPG</filename>
	<path>53.JPG</path>
	<source>
		<database>Unknown</database>
	</source>
	<size>
		<width>1920</width>
		<height>1080</height>
		<depth>3</depth>
	</size>
	<segmented>0</segmented>
	<object>
		<name>6_patch</name>
		<pose>Unspecified</pose>
		<truncated>0</truncated>
		<difficult>0</difficult>
		<bndbox>
			<xmin>409</xmin>
			<ymin>495</ymin>
			<xmax>662</xmax>
			<ymax>585</ymax>
		</bndbox>
	</object>
	<object>
		<name>4_mediumsquare</name>
		<pose>Unspecified</pose>
		<truncated>0</truncated>
		<difficult>0</difficult>
		<bndbox>
			<xmin>208</xmin>
			<ymin>829</ymin>
			<xmax>681</xmax>
			<ymax>1031</ymax>
		</bndbox>
	</object>
	<object>
		<name>6_patch</name>
		<pose>Unspecified</pose>
		<truncated>0</truncated>
		<difficult>0</difficult>
		<bndbox>
			<xmin>697</xmin>
			<ymin>590</ymin>
			<xmax>950</xmax>
			<ymax>680</ymax>
		</bndbox>
	</object>
	<object>
		<name>6_patch</name>
		<pose>Unspecified</pose>
		<truncated>0</truncated>
		<difficult>0</difficult>
		<bndbox>
			<xmin>1021</xmin>
			<ymin>497</ymin>
			<xmax>1229</xmax>
			<ymax>564</ymax>
		</bndbox>
	</object>
	<object>
		<name>6_patch</name>
		<pose>Unspecified</pose>
		<truncated>0</truncated>
		<difficult>0</difficult>
		<bndbox>
			<xmin>1276</xmin>
			<ymin>541</ymin>
			<xmax>1484</xmax>
			<ymax>608</ymax>
		</bndbox>
	</object>
	<object>
		<name>6_patch</name>
		<pose>Unspecified</pose>
		<truncated>0</truncated>
		<difficult>0</difficult>
		<bndbox>
			<xmin>1533</xmin>
			<ymin>863</ymin>
			<xmax>1741</xmax>
			<ymax>930</ymax>
		</bndbox>
	</object>
	<object>
		<name>6_patch</name>
		<pose>Unspecified</pose>
		<truncated>0</truncated>
		<difficult>0</difficult>
		<bndbox>
			<xmin>1270</xmin>
			<ymin>779</ymin>
			<xmax>1478</xmax>
			<ymax>846</ymax>
		</bndbox>
	</object>
</annotation>